defines.vh
`ifndef DEFINES_VH
`define DEFINES_VH

`define DATA_WIDTH 8
`define ACC_WIDTH 20

`endif

uart_tx.v
module uart_tx 
  #(parameter CLKS_PER_BIT = 10) // Matching this number to receiver unit!
  (
   input wire       clk,
   input wire       reset_n,
   input wire       tx_start, // Pulse HIGH to start sending
   input wire [7:0] tx_data,  // Byte to send
   output reg       tx_active, // High while sending
   output reg       tx_serial, // The wire to Python
   output reg       tx_done    // High when finished
   );
 
  localparam s_IDLE         = 3'b000;
  localparam s_TX_START_BIT = 3'b001;
  localparam s_TX_DATA_BITS = 3'b010;
  localparam s_TX_STOP_BIT  = 3'b011;
  localparam s_CLEANUP      = 3'b100;
   
  reg [2:0]    r_SM_Main;
  reg [13:0]   r_Clock_Count;
  reg [2:0]    r_Bit_Index;
  reg [7:0]    r_Tx_Data;
   
  always @(posedge clk or negedge reset_n) begin
    if (!reset_n) begin
      r_SM_Main <= s_IDLE;
      tx_active <= 0;
      tx_serial <= 1; // Idle state for UART is High
      tx_done   <= 0;
      r_Clock_Count <= 0;
      r_Bit_Index <= 0;
      r_Tx_Data <= 0;
    end else begin
       
      case (r_SM_Main)
        s_IDLE : begin
          tx_active <= 0;
          tx_serial <= 1;
          tx_done   <= 0;
          r_Clock_Count <= 0;
          r_Bit_Index <= 0;
           
          if (tx_start == 1'b1) begin
            tx_active <= 1;
            r_Tx_Data <= tx_data;
            r_SM_Main <= s_TX_START_BIT;
          end
        end
         
        s_TX_START_BIT : begin
          tx_serial <= 0; // Start bit = Low
          if (r_Clock_Count < CLKS_PER_BIT-1) begin
            r_Clock_Count <= r_Clock_Count + 1;
          end else begin
            r_Clock_Count <= 0;
            r_SM_Main     <= s_TX_DATA_BITS;
          end
        end
         
        s_TX_DATA_BITS : begin
          tx_serial <= r_Tx_Data[r_Bit_Index];
           
          if (r_Clock_Count < CLKS_PER_BIT-1) begin
            r_Clock_Count <= r_Clock_Count + 1;
          end else begin
            r_Clock_Count <= 0;
            if (r_Bit_Index < 7) begin
              r_Bit_Index <= r_Bit_Index + 1;
            end else begin
              r_Bit_Index <= 0;
              r_SM_Main   <= s_TX_STOP_BIT;
            end
          end
        end
         
        s_TX_STOP_BIT : begin
          tx_serial <= 1; // Stop bit = High
          if (r_Clock_Count < CLKS_PER_BIT-1) begin
            r_Clock_Count <= r_Clock_Count + 1;
          end else begin
            tx_done       <= 1;
            r_Clock_Count <= 0;
            r_SM_Main     <= s_CLEANUP;
            tx_active     <= 0;
          end
        end
         
        s_CLEANUP : begin
          tx_done   <= 1;
          r_SM_Main <= s_IDLE;
        end
         
        default : r_SM_Main <= s_IDLE;
      endcase
    end
  end
endmodule

activation_unit.v
`include "defines.vh"

module activation_unit (
	input wire [1:0] activation_type,
	input signed [`ACC_WIDTH-1:0] data_in, //input from MAC unit
	output reg signed [`DATA_WIDTH-1:0] data_out //8-bit signed output to next layer 
);

	parameter SIGNED_THRESHOLD = 0;

    // Define Max Positive Value for 8-bit signed (01111111 = 127)
    parameter MAX_VAL = 8'sd127; 

    always @(*) begin
        case (activation_type)
            // --- Mode 0: ReLU (Rectified Linear Unit) for hidden layer---
            2'b00: begin
                if (data_in < 0) 
                    data_out = 8'sd0; // Block negative values
                else begin
                    // Saturation Logic: If value is too big for 8 bits, cap it at MAX
                    if (data_in > MAX_VAL) 
                        data_out = MAX_VAL;
                    else 
                        data_out = data_in[`DATA_WIDTH-1:0]; // Truncate/Pass through
                end
            end

            // --- Mode 1: Step Function (Threshold) for output layers---
            2'b01: begin
                if (data_in > SIGNED_THRESHOLD) 
                    data_out = MAX_VAL; // "Yes" / Class Detected (High)
                else 
                    data_out = 8'sd0;   // "No" / Nothing (Low)
            end

            // --- Mode 2: Passthrough (Linear) ---
            // Useful for debugging or regression tasks
            default: begin
                 // Simple saturation logic
                 if (data_in > MAX_VAL) data_out = MAX_VAL;
                 else if (data_in < -128) data_out = -8'sd128; // Min signed 8-bit
                 else data_out = data_in[`DATA_WIDTH-1:0];
            end
        endcase
    end

endmodule

mac_unit.v
`include "defines.vh"

module mac_unit(
	input clk,
	input reset_n,
	input clear_acc,
	input enable,
	input signed [`DATA_WIDTH-1:0] weight_val,  //uses signed values to correctly handle negative weights.
	input signed [`DATA_WIDTH-1:0] input_val,
	output signed [`ACC_WIDTH-1:0] accumulated_result
);

	wire signed [(`DATA_WIDTH*2)-1:0] product;
	reg  signed [`ACC_WIDTH-1:0] accumulator;
	
	//Multiplication Stage
	assign product = weight_val * input_val;
	
	//Accumulation Stage
	always@(posedge clk or negedge reset_n) 
	begin
	if(!reset_n) begin
	accumulator <= 0;
	end
	else if (clear_acc) begin
	accumulator <= 0;
	end
	else if (enable) begin
	accumulator <= accumulator  + product;
	end
	end
	
	assign accumulated_result = accumulator;
	
endmodule

hidden_layer.v
`include "defines.vh"

module hidden_layer(
	input wire clk,
	input wire reset_n,
	input wire start_layer,
	input wire data_valid,
	input wire signed [`DATA_WIDTH-1:0] input_pixel,  //single pixel 8-bit


	//memory interface
	output reg [7:0] weight_address_base,
	input wire signed [`DATA_WIDTH-1:0] weight_n0,
	input wire signed [`DATA_WIDTH-1:0] weight_n1,
	input wire signed [`DATA_WIDTH-1:0] weight_n2,
	input wire signed [`DATA_WIDTH-1:0] weight_n3,
	
	//Configurable datapath interface
	input wire [1:0]activation_type,
	
	//output (the final score after all pixel's are processed)
	output wire signed [`DATA_WIDTH-1:0] out_n0,
	output wire signed [`DATA_WIDTH-1:0] out_n1,
	output wire signed [`DATA_WIDTH-1:0] out_n2,
	output wire signed [`DATA_WIDTH-1:0] out_n3
	
);

//Internal wires for MAC outputs {20-bit}
wire signed [`ACC_WIDTH-1:0] acc_n0,acc_n1,acc_n2,acc_n3;


// --- 1. Address Counter Logic ---
    // This tells the memory which weight to fetch for the current pixel
    always @(posedge clk or negedge reset_n) begin
        if (!reset_n) begin
            weight_address_base <= 0;
        end else if (start_layer) begin
            weight_address_base <= 0; // Reset counter for new image
        end else if (data_valid) begin
            weight_address_base <= weight_address_base + 1; // Move to next weight
        end
    end

//Instantiating neurons with same input and different weights

mac_unit mac0 (
	.clk(clk), .reset_n(reset_n), .clear_acc(start_layer), .enable(data_valid),
	.weight_val(weight_n0), .input_val(input_pixel),.accumulated_result(acc_n0)
);


mac_unit mac1 (
	.clk(clk), .reset_n(reset_n), .clear_acc(start_layer), .enable(data_valid),
	.weight_val(weight_n1), .input_val(input_pixel),.accumulated_result(acc_n1)
);

mac_unit mac2 (
	.clk(clk), .reset_n(reset_n), .clear_acc(start_layer), .enable(data_valid),
	.weight_val(weight_n2), .input_val(input_pixel),.accumulated_result(acc_n2)
);

mac_unit mac3 (
	.clk(clk), .reset_n(reset_n), .clear_acc(start_layer), .enable(data_valid),
	.weight_val(weight_n3), .input_val(input_pixel),.accumulated_result(acc_n3)
);


//Activation logic & convert the 20-bit accumulator output to 8-bit

activation_unit act0(.activation_type(activation_type),.data_in(acc_n0), .data_out(out_n0));
activation_unit act1(.activation_type(activation_type),.data_in(acc_n1), .data_out(out_n1));
activation_unit act2(.activation_type(activation_type),.data_in(acc_n2), .data_out(out_n2));
activation_unit act3(.activation_type(activation_type),.data_in(acc_n3), .data_out(out_n3));

endmodule

weight_memory.v
`include "defines.vh"

module weight_memory (
	input wire clk,
	
	//PORT A: Connected to UART
	input wire write_en,
	input wire [7:0] write_addr,
	input wire signed [`DATA_WIDTH-1:0] write_data,
	
	//PORT B: Connected to MAC_units
	input wire [7:0] read_addr,
	output reg signed [`DATA_WIDTH-1:0] read_data
);

	//Defining MEMORY ARRAY
	reg signed [`DATA_WIDTH-1:0] mem_array[0:63];
	
	always@(posedge clk)
	begin
	if(write_en) begin
	mem_array[write_addr] <= write_data;
	end
	end
	
	//combinational read is faster 
	always@(*)
	begin
	read_data = mem_array[read_addr];
	end
endmodule

control_fsm.v
`include "defines.vh"

module control_fsm (
    input wire clk,
    input wire reset_n,
    input wire rx_done,          // "New byte arrived from Python"
    
    output reg write_en,         // 1 = Write to Memory, 0 = Don't Write
    output reg [7:0] write_addr, // Where to write the weight
    output reg start_compute     // 1 = Reset Layer Accumulators
);

    // --- State Encoding ---
    localparam STATE_LOAD_WEIGHTS = 2'b00;
    localparam STATE_START_COMPUTE = 2'b01;
    localparam STATE_RUNNING       = 2'b10;

    reg [1:0] state;
    
    // Define how many weights we expect before switching modes
    // 4 neurons * 16 weights (example) = 64 bytes
    // this should match the number of bytes your Python script sends!
    localparam TOTAL_WEIGHTS = 8'd64; 

    always @(posedge clk or negedge reset_n) begin
        if (!reset_n) begin
            state <= STATE_LOAD_WEIGHTS;
            write_addr <= 0;
            write_en <= 0;
            start_compute <= 0;
        end else begin
            case (state)
                
                // --- STATE 0: LOAD MODE ---
                // Listen to UART, fill memory, count up to 64
                STATE_LOAD_WEIGHTS: begin
                    start_compute <= 0;
                    
                    if (rx_done) begin
                        write_en <= 1; 
                        if (write_addr == TOTAL_WEIGHTS - 1) begin
                            state <= STATE_START_COMPUTE;
                        end else begin
                            write_addr <= write_addr + 1; 
                        end
                    end else begin
                        write_en <= 0; 
                    end
                end

                // --- STATE 1: RESET TRIGGER ---
                // Clear the Neural Network accumulators once
                STATE_START_COMPUTE: begin
                    write_en <= 0;       
                    start_compute <= 1;  // Pulse High to Reset Accumulators
                    state <= STATE_RUNNING;
                end

                // --- STATE 2: RUNNING MODE ---
                // FSM just sits here. The logic in top_accelerator handles the 
                // RX -> MAC -> TX pipeline.
                STATE_RUNNING: begin
                    start_compute <= 0; // Release Reset
                    write_en <= 0;      
                end
                
            endcase
        end
    end

endmodule

uart_rx.v
module uart_rx 
  #(parameter CLKS_PER_BIT = 10) // sending only 10 bits to check using testbench
  (
   input wire        clk,
   input wire        reset_n,
   input wire        rx_in,
   output reg [7:0]  rx_data,
   output reg        rx_done
   );

  localparam s_IDLE         = 3'b000;
  localparam s_RX_START_BIT = 3'b001;
  localparam s_RX_DATA_BITS = 3'b010;
  localparam s_RX_STOP_BIT  = 3'b011;
  localparam s_CLEANUP      = 3'b100;

  reg [2:0]     r_SM_Main;
  reg [13:0]    r_Clock_Count;
  reg [2:0]     r_Bit_Index;
  reg           r_Rx_Data_R;
  reg           r_Rx_Data;

  // Double-register the incoming data to sync with clock (Anti-Metastability)
  always @(posedge clk) begin
      r_Rx_Data_R <= rx_in;
      r_Rx_Data   <= r_Rx_Data_R;
  end

  // State Machine
  always @(posedge clk or negedge reset_n) begin
      if (!reset_n) begin
          r_SM_Main <= s_IDLE;
          rx_done <= 0;
          r_Clock_Count <= 0;
          r_Bit_Index <= 0;
          rx_data <= 0;
      end else begin
          case (r_SM_Main)
            s_IDLE : begin
              rx_done <= 1'b0;
              r_Clock_Count <= 0;
              r_Bit_Index <= 0;
              if (r_Rx_Data == 1'b0) begin // Start bit detected
                r_SM_Main <= s_RX_START_BIT;
              end
            end

            s_RX_START_BIT : begin
              if (r_Clock_Count == (CLKS_PER_BIT-1)/2) begin
                if (r_Rx_Data == 1'b0) begin
                  r_Clock_Count <= 0;
                  r_SM_Main     <= s_RX_DATA_BITS;
                end else
                  r_SM_Main <= s_IDLE;
              end else begin
                r_Clock_Count <= r_Clock_Count + 1;
              end
            end

            s_RX_DATA_BITS : begin
              if (r_Clock_Count < CLKS_PER_BIT-1) begin
                r_Clock_Count <= r_Clock_Count + 1;
              end else begin
                r_Clock_Count          <= 0;
                rx_data[r_Bit_Index] <= r_Rx_Data;
                if (r_Bit_Index < 7) begin
                  r_Bit_Index <= r_Bit_Index + 1;
                end else begin
                  r_Bit_Index <= 0;
                  r_SM_Main   <= s_RX_STOP_BIT;
                end
              end
            end

            s_RX_STOP_BIT : begin
              if (r_Clock_Count < CLKS_PER_BIT-1) begin
                r_Clock_Count <= r_Clock_Count + 1;
              end else begin
                rx_done       <= 1'b1; // Pulse Done!
                r_Clock_Count <= 0;
                r_SM_Main     <= s_CLEANUP;
              end
            end

            s_CLEANUP : begin
              r_SM_Main <= s_IDLE;
              rx_done   <= 1'b0;
            end
            
            default : r_SM_Main <= s_IDLE;
          endcase
      end
  end
endmodule

top_accelerator.v
`include "defines.vh"

module top_accelerator (
    input wire clk,
    input wire reset_n,
    input wire rx_in,             // UART Input (From Python)
    output wire tx_out            // UART Output (To Python)
);

    // --- SIGNALS ---
    wire [7:0] rx_data;
    wire rx_done;

    // FSM Signals
    wire write_enable_mem;
    wire start_compute; // This is the 'reset accumulator' signal
    wire [7:0] write_addr;
    wire [7:0] layer_read_addr; 
    
    // Weights & Outputs
    wire signed [`DATA_WIDTH-1:0] w0, w1, w2, w3;
    wire signed [`DATA_WIDTH-1:0] n0_out, n1_out, n2_out, n3_out;

    // --- TX LOGIC SIGNALS ---
    reg tx_start_reg;
    reg [1:0] tx_delay_cnt; // To wait for MAC calculation
    wire tx_active, tx_done_sig;

    // --- 1. UART RX ---
    uart_rx u_rx (
        .clk(clk), .reset_n(reset_n),
        .rx_in(rx_in),
        .rx_data(rx_data),
        .rx_done(rx_done)
    );

    // --- 2. THE FSM ---
    control_fsm u_fsm (
        .clk(clk), .reset_n(reset_n),
        .rx_done(rx_done),       
        .write_en(write_enable_mem), 
        .write_addr(write_addr),     
        .start_compute(start_compute) 
    );

    // --- 3. MEMORY BANKS ---
    weight_memory bank0 (.clk(clk), .write_en(write_enable_mem), .write_addr(write_addr), .write_data(rx_data), .read_addr(layer_read_addr), .read_data(w0));
    weight_memory bank1 (.clk(clk), .write_en(write_enable_mem), .write_addr(write_addr), .write_data(rx_data), .read_addr(layer_read_addr), .read_data(w1));
    weight_memory bank2 (.clk(clk), .write_en(write_enable_mem), .write_addr(write_addr), .write_data(rx_data), .read_addr(layer_read_addr), .read_data(w2));
    weight_memory bank3 (.clk(clk), .write_en(write_enable_mem), .write_addr(write_addr), .write_data(rx_data), .read_addr(layer_read_addr), .read_data(w3));

    // --- 4. THE Hidden Layer ---
    hidden_layer u_layer2 (
        .clk(clk), .reset_n(reset_n),
        .start_layer(start_compute),
        .data_valid(rx_done), // Compute trigger
        .input_pixel(rx_data), 
        .weight_address_base(layer_read_addr),
        .weight_n0(w0), .weight_n1(w1), .weight_n2(w2), .weight_n3(w3),
        .activation_type(2'b00), 
        .out_n0(n0_out), .out_n1(n1_out), .out_n2(n2_out), .out_n3(n3_out)
    );

    // --- 5. TX TRIGGER LOGIC (New!) ---
    // We only want to send data back when we are in COMPUTING mode, not LOADING mode.
    // from FSM If write_enable_mem is LOW and start_compute is LOW (Running state), we are computing.
    
    always @(posedge clk or negedge reset_n) begin
        if (!reset_n) begin
            tx_start_reg <= 0;
            tx_delay_cnt <= 0;
        end else begin
            // Default
            tx_start_reg <= 0;

            // Logic: If we received a byte (rx_done) AND we are NOT loading weights
            if (rx_done && !write_enable_mem && !start_compute) begin
                tx_delay_cnt <= 1; // Start delay timer
            end
            
            // Wait 1 cycle for MAC to finish, then fire TX
            if (tx_delay_cnt == 1) begin
                tx_delay_cnt <= 2;
            end else if (tx_delay_cnt == 2) begin
                tx_start_reg <= 1; // FIRE!
                tx_delay_cnt <= 0; // Reset
            end
        end
    end

    // --- 6. UART TX (Sends Result) ---
    uart_tx u_tx (
        .clk(clk), .reset_n(rst_n),
        .tx_start(tx_start_reg),
        .tx_data(n0_out), // Send Neuron 0's result (or use Mux to cycle through them)
        .tx_active(tx_active),
        .tx_serial(tx_out),
        .tx_done(tx_done_sig)
    );

endmodule

top_accelerator_tb.v
`timescale 1ns / 1ps
`include "defines.vh"

module top_accelerator_tb;

    // --- DUT Signals ---
    reg clk;
    reg reset_n;
    reg rx_in;          // Input TO the FPGA
    wire tx_out;        // Output FROM the FPGA

    // --- Simulation Parameters ---
    localparam CLKS_PER_BIT = 10; 
    localparam BIT_PERIOD = 100; // 10 clocks * 10ns period

    // --- Instantiate the Full System ---
    top_accelerator u_dut (
        .clk(clk),
        .reset_n(reset_n),
        .rx_in(rx_in),
        .tx_out(tx_out)
    );

    // --- Clock Generation ---
    always #5 clk = ~clk; // 100 MHz

    // --- TASK: SEND BYTE (Simulates Python Writing) ---
    task send_byte_to_fpga;
        input [7:0] data_to_send;
        integer i;
        begin
            rx_in = 0; #(BIT_PERIOD); // Start Bit
            for (i=0; i<8; i=i+1) begin
                rx_in = data_to_send[i]; #(BIT_PERIOD);
            end
            rx_in = 1; #(BIT_PERIOD); // Stop Bit
        end
    endtask

    // --- NEW TASK: RECEIVE BYTE (Simulates Python Reading) ---
    reg [7:0] received_data; // Buffer to store the byte
    task wait_and_receive_byte;
        integer i;
        begin
            // 1. Wait for the FPGA to pull the line LOW (Start Bit)
            @(negedge tx_out);
            
            // 2. Wait 1.5 bit periods to get to the middle of the first data bit
            #(BIT_PERIOD + (BIT_PERIOD/2));
            
            // 3. Sample 8 Bits
            for (i=0; i<8; i=i+1) begin
                received_data[i] = tx_out;
                #(BIT_PERIOD);
            end
            
            // 4. Print the result to the terminal!
            $display("\n------------------------------------------------");
            $display("PYTHON RECEIVED: %d (Binary: %b)", received_data, received_data);
            $display("------------------------------------------------\n");
        end
    endtask

    // --- TEST PROCEDURE ---
    integer w;
    initial begin
        $dumpfile("full_system.vcd");
        $dumpvars(0, top_accelerator_tb);

        // 1. Initialize
        clk = 0;
        reset_n = 0;
        rx_in = 1; // UART Idle is High
        #100;
        reset_n = 1;
        #100;

        // --- PHASE 1: LOAD WEIGHTS ---
        $display("--- PHASE 1: Loading Weights (Simulating Python) ---");
        
        // Loop 64 times to load weights
        for (w=0; w<64; w=w+1) begin
            // Send unique weights (w+1) so we don't multiply by zero!
            send_byte_to_fpga(w + 1); 
            #1000; 
        end
        $display("Weights Loaded!");

        // --- PHASE 2: SEND PIXEL & LISTEN FOR ANSWER ---
        $display("--- PHASE 2: Sending Pixel Data & Listening ---");
        
        // We use 'fork..join' so we can SEND and LISTEN at the same time
        fork
            // Thread 1: Send the Pixel (Value = 10)
            begin
                #100; // Small delay
                send_byte_to_fpga(8'd10);
            end
            
            // Thread 2: Listen for the result
            begin
                wait_and_receive_byte();
            end
        join

        // Calculation Check:
        // Input (10) * Weight_0 (1) = 10.
        // Expected Output: 10.
        
        #1000;
        $finish;
    end

endmodule

full_system.vcd
$date
	Sat Dec  6 21:28:00 2025
$end
$version
	Icarus Verilog
$end
$timescale
	1ps
$end
$scope module top_accelerator_tb $end
$var wire 1 ! tx_out $end
$var reg 1 " clk $end
$var reg 8 # received_data [7:0] $end
$var reg 1 $ reset_n $end
$var reg 1 % rx_in $end
$var integer 32 & w [31:0] $end
$scope module u_dut $end
$var wire 1 " clk $end
$var wire 1 $ reset_n $end
$var wire 1 ' rst_n $end
$var wire 1 % rx_in $end
$var wire 1 ( write_enable_mem $end
$var wire 8 ) write_addr [7:0] $end
$var wire 8 * w3 [7:0] $end
$var wire 8 + w2 [7:0] $end
$var wire 8 , w1 [7:0] $end
$var wire 8 - w0 [7:0] $end
$var wire 1 ! tx_out $end
$var wire 1 . tx_done_sig $end
$var wire 1 / tx_active $end
$var wire 1 0 start_compute $end
$var wire 1 1 rx_done $end
$var wire 8 2 rx_data [7:0] $end
$var wire 8 3 n3_out [7:0] $end
$var wire 8 4 n2_out [7:0] $end
$var wire 8 5 n1_out [7:0] $end
$var wire 8 6 n0_out [7:0] $end
$var wire 8 7 layer_read_addr [7:0] $end
$var reg 2 8 tx_delay_cnt [1:0] $end
$var reg 1 9 tx_start_reg $end
$scope module bank0 $end
$var wire 1 " clk $end
$var wire 1 ( write_en $end
$var wire 8 : write_data [7:0] $end
$var wire 8 ; write_addr [7:0] $end
$var wire 8 < read_addr [7:0] $end
$var reg 8 = read_data [7:0] $end
$upscope $end
$scope module bank1 $end
$var wire 1 " clk $end
$var wire 1 ( write_en $end
$var wire 8 > write_data [7:0] $end
$var wire 8 ? write_addr [7:0] $end
$var wire 8 @ read_addr [7:0] $end
$var reg 8 A read_data [7:0] $end
$upscope $end
$scope module bank2 $end
$var wire 1 " clk $end
$var wire 1 ( write_en $end
$var wire 8 B write_data [7:0] $end
$var wire 8 C write_addr [7:0] $end
$var wire 8 D read_addr [7:0] $end
$var reg 8 E read_data [7:0] $end
$upscope $end
$scope module bank3 $end
$var wire 1 " clk $end
$var wire 1 ( write_en $end
$var wire 8 F write_data [7:0] $end
$var wire 8 G write_addr [7:0] $end
$var wire 8 H read_addr [7:0] $end
$var reg 8 I read_data [7:0] $end
$upscope $end
$scope module u_fsm $end
$var wire 1 " clk $end
$var wire 1 $ reset_n $end
$var wire 1 1 rx_done $end
$var reg 1 0 start_compute $end
$var reg 2 J state [1:0] $end
$var reg 8 K write_addr [7:0] $end
$var reg 1 ( write_en $end
$upscope $end
$scope module u_layer2 $end
$var wire 2 L activation_type [1:0] $end
$var wire 1 " clk $end
$var wire 1 $ reset_n $end
$var wire 1 0 start_layer $end
$var wire 8 M weight_n0 [7:0] $end
$var wire 8 N weight_n1 [7:0] $end
$var wire 8 O weight_n2 [7:0] $end
$var wire 8 P weight_n3 [7:0] $end
$var wire 8 Q out_n3 [7:0] $end
$var wire 8 R out_n2 [7:0] $end
$var wire 8 S out_n1 [7:0] $end
$var wire 8 T out_n0 [7:0] $end
$var wire 8 U input_pixel [7:0] $end
$var wire 1 1 data_valid $end
$var wire 20 V acc_n3 [19:0] $end
$var wire 20 W acc_n2 [19:0] $end
$var wire 20 X acc_n1 [19:0] $end
$var wire 20 Y acc_n0 [19:0] $end
$var reg 8 Z weight_address_base [7:0] $end
$scope module act0 $end
$var wire 2 [ activation_type [1:0] $end
$var wire 20 \ data_in [19:0] $end
$var reg 8 ] data_out [7:0] $end
$upscope $end
$scope module act1 $end
$var wire 2 ^ activation_type [1:0] $end
$var wire 20 _ data_in [19:0] $end
$var reg 8 ` data_out [7:0] $end
$upscope $end
$scope module act2 $end
$var wire 2 a activation_type [1:0] $end
$var wire 20 b data_in [19:0] $end
$var reg 8 c data_out [7:0] $end
$upscope $end
$scope module act3 $end
$var wire 2 d activation_type [1:0] $end
$var wire 20 e data_in [19:0] $end
$var reg 8 f data_out [7:0] $end
$upscope $end
$scope module mac0 $end
$var wire 20 g accumulated_result [19:0] $end
$var wire 1 0 clear_acc $end
$var wire 1 " clk $end
$var wire 1 $ reset_n $end
$var wire 8 h weight_val [7:0] $end
$var wire 16 i product [15:0] $end
$var wire 8 j input_val [7:0] $end
$var wire 1 1 enable $end
$var reg 20 k accumulator [19:0] $end
$upscope $end
$scope module mac1 $end
$var wire 20 l accumulated_result [19:0] $end
$var wire 1 0 clear_acc $end
$var wire 1 " clk $end
$var wire 1 $ reset_n $end
$var wire 8 m weight_val [7:0] $end
$var wire 16 n product [15:0] $end
$var wire 8 o input_val [7:0] $end
$var wire 1 1 enable $end
$var reg 20 p accumulator [19:0] $end
$upscope $end
$scope module mac2 $end
$var wire 20 q accumulated_result [19:0] $end
$var wire 1 0 clear_acc $end
$var wire 1 " clk $end
$var wire 1 $ reset_n $end
$var wire 8 r weight_val [7:0] $end
$var wire 16 s product [15:0] $end
$var wire 8 t input_val [7:0] $end
$var wire 1 1 enable $end
$var reg 20 u accumulator [19:0] $end
$upscope $end
$scope module mac3 $end
$var wire 20 v accumulated_result [19:0] $end
$var wire 1 0 clear_acc $end
$var wire 1 " clk $end
$var wire 1 $ reset_n $end
$var wire 8 w weight_val [7:0] $end
$var wire 16 x product [15:0] $end
$var wire 8 y input_val [7:0] $end
$var wire 1 1 enable $end
$var reg 20 z accumulator [19:0] $end
$upscope $end
$upscope $end
$scope module u_rx $end
$var wire 1 " clk $end
$var wire 1 $ reset_n $end
$var wire 1 % rx_in $end
$var reg 3 { r_Bit_Index [2:0] $end
$var reg 14 | r_Clock_Count [13:0] $end
$var reg 1 } r_Rx_Data $end
$var reg 1 ~ r_Rx_Data_R $end
$var reg 3 !" r_SM_Main [2:0] $end
$var reg 8 "" rx_data [7:0] $end
$var reg 1 1 rx_done $end
$upscope $end
$scope module u_tx $end
$var wire 1 " clk $end
$var wire 1 ' reset_n $end
$var wire 8 #" tx_data [7:0] $end
$var wire 1 9 tx_start $end
$var reg 3 $" r_Bit_Index [2:0] $end
$var reg 14 %" r_Clock_Count [13:0] $end
$var reg 3 &" r_SM_Main [2:0] $end
$var reg 8 '" r_Tx_Data [7:0] $end
$var reg 1 / tx_active $end
$var reg 1 . tx_done $end
$var reg 1 ! tx_serial $end
$upscope $end
$upscope $end
$scope task send_byte_to_fpga $end
$var reg 8 (" data_to_send [7:0] $end
$var integer 32 )" i [31:0] $end
$upscope $end
$scope task wait_and_receive_byte $end
$var integer 32 *" i [31:0] $end
$upscope $end
$upscope $end
$enddefinitions $end
#0
$dumpvars
bx *"
bx )"
bx ("
bx '"
bx &"
bx %"
bx $"
b0 #"
b0 ""
b0 !"
x~
x}
b0 |
b0 {
b0 z
b0 y
bx x
bx w
b0 v
b0 u
b0 t
bx s
bx r
b0 q
b0 p
b0 o
bx n
bx m
b0 l
b0 k
b0 j
bx i
bx h
b0 g
b0 f
b0 e
b0 d
b0 c
b0 b
b0 a
b0 `
b0 _
b0 ^
b0 ]
b0 \
b0 [
b0 Z
b0 Y
b0 X
b0 W
b0 V
b0 U
b0 T
b0 S
b0 R
b0 Q
bx P
bx O
bx N
bx M
b0 L
b0 K
b0 J
bx I
b0 H
b0 G
b0 F
bx E
b0 D
b0 C
b0 B
bx A
b0 @
b0 ?
b0 >
bx =
b0 <
b0 ;
b0 :
09
b0 8
b0 7
b0 6
b0 5
b0 4
b0 3
b0 2
01
00
x/
x.
bx -
bx ,
bx +
bx *
b0 )
0(
z'
bx &
1%
0$
bx #
0"
x!
$end
#5000
1~
b0 &"
1"
#10000
0"
#15000
1}
b0 $"
b0 %"
0.
1!
0/
1"
#20000
0"
#25000
1"
#30000
0"
#35000
1"
#40000
0"
#45000
1"
#50000
0"
#55000
1"
#60000
0"
#65000
1"
#70000
0"
#75000
1"
#80000
0"
#85000
1"
#90000
0"
#95000
1"
#100000
0"
1$
#105000
1"
#110000
0"
#115000
1"
#120000
0"
#125000
1"
#130000
0"
#135000
1"
#140000
0"
#145000
1"
#150000
0"
#155000
1"
#160000
0"
#165000
1"
#170000
0"
#175000
1"
#180000
0"
#185000
1"
#190000
0"
#195000
1"
#200000
0"
0%
b1 ("
b0 &
#205000
0~
1"
#210000
0"
#215000
0}
1"
#220000
0"
#225000
b1 !"
1"
#230000
0"
#235000
b1 |
1"
#240000
0"
#245000
b10 |
1"
#250000
0"
#255000
b11 |
1"
#260000
0"
#265000
b100 |
1"
#270000
0"
#275000
b101 |
1"
#280000
0"
#285000
b10 !"
b0 |
1"
#290000
0"
#295000
b1 |
1"
#300000
0"
#305000
b10 |
1"
#310000
0"
1%
b0 )"
#315000
1~
b11 |
1"
#320000
0"
#325000
1}
b100 |
1"
#330000
0"
#335000
b101 |
1"
#340000
0"
#345000
b110 |
1"
#350000
0"
#355000
b111 |
1"
#360000
0"
#365000
b1000 |
1"
#370000
0"
#375000
b1001 |
1"
#380000
0"
#385000
b1010 |
1"
#390000
0"
#395000
b1 {
b1 2
b1 :
b1 >
b1 B
b1 F
b1 U
b1 j
b1 o
b1 t
b1 y
b1 ""
b0 |
1"
#400000
0"
#405000
b1 |
1"
#410000
0"
#415000
b10 |
1"
#420000
0"
0%
b1 )"
#425000
0~
b11 |
1"
#430000
0"
#435000
0}
b100 |
1"
#440000
0"
#445000
b101 |
1"
#450000
0"
#455000
b110 |
1"
#460000
0"
#465000
b111 |
1"
#470000
0"
#475000
b1000 |
1"
#480000
0"
#485000
b1001 |
1"
#490000
0"
#495000
b1010 |
1"
#500000
0"
#505000
b10 {
b0 |
1"
#510000
0"
#515000
b1 |
1"
#520000
0"
#525000
b10 |
1"
#530000
0"
b10 )"
#535000
b11 |
1"
#540000
0"
#545000
b100 |
1"
#550000
0"
#555000
b101 |
1"
#560000
0"
#565000
b110 |
1"
#570000
0"
#575000
b111 |
1"
#580000
0"
#585000
b1000 |
1"
#590000
0"
#595000
b1001 |
1"
#600000
0"
#605000
b1010 |
1"
#610000
0"
#615000
b11 {
b0 |
1"
#620000
0"
#625000
b1 |
1"
#630000
0"
#635000
b10 |
1"
#640000
0"
b11 )"
#645000
b11 |
1"
#650000
0"
#655000
b100 |
1"
#660000
0"
#665000
b101 |
1"
#670000
0"
#675000
b110 |
1"
#680000
0"
#685000
b111 |
1"
#690000
0"
#695000
b1000 |
1"
#700000
0"
#705000
b1001 |
1"
#710000
0"
#715000
b1010 |
1"
#720000
0"
#725000
b100 {
b0 |
1"
#730000
0"
#735000
b1 |
1"
#740000
0"
#745000
b10 |
1"
#750000
0"
b100 )"
#755000
b11 |
1"
#760000
0"
#765000
b100 |
1"
#770000
0"
#775000
b101 |
1"
#780000
0"
#785000
b110 |
1"
#790000
0"
#795000
b111 |
1"
#800000
0"
#805000
b1000 |
1"
#810000
0"
#815000
b1001 |
1"
#820000
0"
#825000
b1010 |
1"
#830000
0"
#835000
b101 {
b0 |
1"
#840000
0"
#845000
b1 |
1"
#850000
0"
#855000
b10 |
1"
#860000
0"
b101 )"
#865000
b11 |
1"
#870000
0"
#875000
b100 |
1"
#880000
0"
#885000
b101 |
1"
#890000
0"
#895000
b110 |
1"
#900000
0"
#905000
b111 |
1"
#910000
0"
#915000
b1000 |
1"
#920000
0"
#925000
b1001 |
1"
#930000
0"
#935000
b1010 |
1"
#940000
0"
#945000
b110 {
b0 |
1"
#950000
0"
#955000
b1 |
1"
#960000
0"
#965000
b10 |
1"
#970000
0"
b110 )"
#975000
b11 |
1"
#980000
0"
#985000
b100 |
1"
#990000
0"
#995000
b101 |
1"
#1000000
0"
#1005000
b110 |
1"
#1010000
0"
#1015000
b111 |
1"
#1020000
0"
#1025000
b1000 |
1"
#1030000
0"
#1035000
b1001 |
1"
#1040000
0"
#1045000
b1010 |
1"
